.gitignore
CHANGES.txt
MANIFEST.in
README.txt
setup.py
docs/INSTALL.txt
docs/LICENSE.GPL
docs/LICENSE.txt
docs/TODO.txt
plone/__init__.py
plone.app.kss.egg-info/PKG-INFO
plone.app.kss.egg-info/SOURCES.txt
plone.app.kss.egg-info/dependency_links.txt
plone.app.kss.egg-info/entry_points.txt
plone.app.kss.egg-info/namespace_packages.txt
plone.app.kss.egg-info/not-zip-safe
plone.app.kss.egg-info/requires.txt
plone.app.kss.egg-info/top_level.txt
plone/app/__init__.py
plone/app/kss/__init__.py
plone/app/kss/calendar.py
plone/app/kss/config.py
plone/app/kss/configure.zcml
plone/app/kss/content_replacer.py
plone/app/kss/globalui.py
plone/app/kss/headerviewlet.py
plone/app/kss/interfaces.py
plone/app/kss/kupu.py
plone/app/kss/macro_replacer.py
plone/app/kss/meta.zcml
plone/app/kss/plonekssview.py
plone/app/kss/portlet_refresher.py
plone/app/kss/portlets.py
plone/app/kss/refresh_content_menu.py
plone/app/kss/browser/macro_wrapper.pt
plone/app/kss/browser/main_template_standalone.pt
plone/app/kss/commands/__init__.py
plone/app/kss/commands/configure.zcml
plone/app/kss/commands/interfaces.py
plone/app/kss/commands/issueportalmessage.py
plone/app/kss/commands/legacycommands.py
plone/app/kss/commands/plonecommands.py
plone/app/kss/commands/portlets.py
plone/app/kss/commands/refreshContentMenu.py
plone/app/kss/commands/refreshViewlet.py
plone/app/kss/commands/refreshportlet.py
plone/app/kss/commands/refreshprovider.py
plone/app/kss/commands/replacecontentmenu.py
plone/app/kss/commands/zopecommands.py
plone/app/kss/demo/__init__.py
plone/app/kss/demo/bbb_oldkssdemo.py
plone/app/kss/demo/configure.zcml
plone/app/kss/demo/demoview.py
plone/app/kss/demo/follow-link.kss
plone/app/kss/demo/follow-link.pt
plone/app/kss/demo/log-in-manager.html
plone/app/kss/demo/log-in-user.html
plone/app/kss/demo/log-out.html
plone/app/kss/demo/site_creation_view.py
plone/app/kss/demo/zopeconfig.py
plone/app/kss/demo/selenium_tests/experimental_disabled/workflow_transition.html
plone/app/kss/demo/selenium_tests/legacy_unused/breadcrumbs.html
plone/app/kss/demo/selenium_tests/legacy_unused/contentmenu_change_tab.html
plone/app/kss/demo/selenium_tests/legacy_unused/contentmenu_presence.html
plone/app/kss/demo/selenium_tests/legacy_unused/folder_contents.html
