Metadata-Version: 1.0
Name: plone.app.kss
Version: 1.8.0
Summary: KSS (Kinetic Style Sheets) for Plone
Home-page: http://pypi.python.org/pypi/plone.app.kss
Author: Plone Foundation
Author-email: plone-developers@lists.sourceforge.net
License: GPL version 2
Platform: UNKNOWN
Classifier: Environment :: Web Environment
Classifier: Framework :: Plone
Classifier: Framework :: Zope2
Classifier: License :: OSI Approved :: GNU General Public License (GPL)
Classifier: Operating System :: OS Independent
Classifier: Programming Language :: Python
